setup.py
IMICTechnology/IMICTechnology.py
IMICTechnology/__init__.py
IMICTechnology.egg-info/PKG-INFO
IMICTechnology.egg-info/SOURCES.txt
IMICTechnology.egg-info/dependency_links.txt
IMICTechnology.egg-info/not-zip-safe
IMICTechnology.egg-info/top_level.txt