Metadata-Version: 2.1
Name: IMICTechnology
Version: 0.1
Summary: Useful features developed by IMIC!
Author: IMIC Technology
